{
  "params": [
    {
      "min_length": 1, 
      "cli_option": [
        "a", 
        "application-name"
      ], 
      "name": "ApplicationName", 
      "optional": false, 
      "max_length": 100, 
      "doc": "  The name of the application to delete the configuration template from.  ", 
      "type": "string"
    }, 
    {
      "min_length": 1, 
      "cli_option": [
        "t", 
        "template-name"
      ], 
      "name": "TemplateName", 
      "optional": false, 
      "max_length": 100, 
      "doc": " The name of the configuration template to delete. ", 
      "type": "string"
    }
  ], 
  "name": "DeleteConfigurationTemplate", 
  "response": {
    "type": "object", 
    "name": "DeleteConfigurationTemplateResponse", 
    "properties": [
      {
        "optional": false, 
        "type": "object", 
        "name": "ResponseMetadata", 
        "properties": [
          {
            "optional": false, 
            "type": "string", 
            "name": "RequestId"
          }
        ]
      }
    ]
  }
}